fuelwatcher/__init__.py
fuelwatcher/constants.py
fuelwatcher/fuelwatch.py
fuelwatcher/models.py
fuelwatcher-1.0.0.dist-info/METADATA
fuelwatcher-1.0.0.dist-info/WHEEL
fuelwatcher-1.0.0.dist-info/licenses/LICENSE.txt
fuelwatcher-1.0.0.dist-info/RECORD
