Metadata-Version: 2.4
Name: fuelwatcher
Version: 1.0.0
Summary: A simple python module that scrapes XML data from the government of Western Australia's FuelWatch website that makes parsing a breeze.
Project-URL: Homepage, https://github.com/danielmichaels/fuelwatcher
Project-URL: Repository, https://github.com/danielmichaels/fuelwatcher
Author-email: Daniel Michaels <dan@danielms.site>
License: MIT
License-File: LICENSE.txt
Requires-Python: >=3.12
Requires-Dist: fake-useragent>=1.5.1
Requires-Dist: requests>=2.28.2
